pyentrp/__init__.py
pyentrp/entropy.py
pyentrp-2.0.0.dist-info/LICENSE
pyentrp-2.0.0.dist-info/METADATA
pyentrp-2.0.0.dist-info/NOTICE
pyentrp-2.0.0.dist-info/WHEEL
pyentrp-2.0.0.dist-info/RECORD
