Metadata-Version: 2.3
Name: pyentrp
Version: 2.0.0
Summary: A Python library for computing entropy measures for time series analysis.
License: Apache-2.0
Author: Nikolay Donets
Author-email: nd@donets.org
Requires-Python: >=3.9,<4.0
Classifier: License :: OSI Approved :: Apache Software License
Classifier: Programming Language :: Python :: 3
Classifier: Programming Language :: Python :: 3.9
Classifier: Programming Language :: Python :: 3.10
Classifier: Programming Language :: Python :: 3.11
Classifier: Programming Language :: Python :: 3.12
Classifier: Programming Language :: Python :: 3.13
Requires-Dist: numpy (>=1.26,<3.0)
